opencv_pg/.DS_Store
opencv_pg/__init__.py
opencv_pg/doc_viewer.py
opencv_pg/launcher.py
opencv_pg/main.py
opencv_pg/pipeline_launcher.py
opencv_pg/robot.jpg
opencv_pg/docs/.DS_Store
opencv_pg/docs/__init__.py
opencv_pg/docs/doc_writer.py
opencv_pg/docs/css/styles.css
opencv_pg/docs/js/.DS_Store
opencv_pg/docs/js/mathjax/.DS_Store
opencv_pg/docs/js/mathjax/core.js
opencv_pg/docs/js/mathjax/latest.js
opencv_pg/docs/js/mathjax/loader.js
opencv_pg/docs/js/mathjax/mml-chtml.js
opencv_pg/docs/js/mathjax/mml-svg.js
opencv_pg/docs/js/mathjax/node-main.js
opencv_pg/docs/js/mathjax/startup.js
opencv_pg/docs/js/mathjax/tex-chtml-full-speech.js
opencv_pg/docs/js/mathjax/tex-chtml-full.js
opencv_pg/docs/js/mathjax/tex-chtml.js
opencv_pg/docs/js/mathjax/tex-mml-chtml.js
opencv_pg/docs/js/mathjax/tex-mml-svg.js
opencv_pg/docs/js/mathjax/tex-svg-full.js
opencv_pg/docs/js/mathjax/tex-svg.js
opencv_pg/docs/js/mathjax/a11y/assistive-mml.js
opencv_pg/docs/js/mathjax/a11y/complexity.js
opencv_pg/docs/js/mathjax/a11y/explorer.js
opencv_pg/docs/js/mathjax/a11y/semantic-enrich.js
opencv_pg/docs/js/mathjax/a11y/sre.js
opencv_pg/docs/js/mathjax/adaptors/liteDOM.js
opencv_pg/docs/js/mathjax/input/.DS_Store
opencv_pg/docs/js/mathjax/input/asciimath.js
opencv_pg/docs/js/mathjax/input/mml.js
opencv_pg/docs/js/mathjax/input/tex-base.js
opencv_pg/docs/js/mathjax/input/tex-full.js
opencv_pg/docs/js/mathjax/input/tex.js
opencv_pg/docs/js/mathjax/input/mml/entities.js
opencv_pg/docs/js/mathjax/input/mml/extensions/mml3.js
opencv_pg/docs/js/mathjax/input/mml/extensions/mml3.sef.json
opencv_pg/docs/js/mathjax/input/tex/extensions/action.js
opencv_pg/docs/js/mathjax/input/tex/extensions/all-packages.js
opencv_pg/docs/js/mathjax/input/tex/extensions/ams.js
opencv_pg/docs/js/mathjax/input/tex/extensions/amscd.js
opencv_pg/docs/js/mathjax/input/tex/extensions/autoload.js
opencv_pg/docs/js/mathjax/input/tex/extensions/bbox.js
opencv_pg/docs/js/mathjax/input/tex/extensions/boldsymbol.js
opencv_pg-1.0.2.dist-info/entry_points.txt
opencv_pg-1.0.2.dist-info/LICENSE.txt
opencv_pg-1.0.2.dist-info/WHEEL
opencv_pg-1.0.2.dist-info/METADATA
opencv_pg-1.0.2.dist-info/RECORD
