Metadata-Version: 2.1
Name: opencv-pg
Version: 1.0.2
Summary: Qt6 GUI Application for realtime exploration of OpenCV functions
Keywords: opencv,cv2,cv,computer vision
Requires-Python: >=3.7
Requires-Dist: pyside6==6.5.2
Requires-Dist: qtpy==2.3.1
Requires-Dist: opencv-contrib-python-headless==4.8.0.76
Requires-Dist: jinja2==3.1.2
Requires-Dist: pytest==6.0.1 ; extra == "dev"
Requires-Dist: flake8 ; extra == "dev"
Requires-Dist: sphinx==3.2.1 ; extra == "dev"
Project-URL: Changelog, https://github.com/opencv-pg/opencv-pg/blob/master/CHANGELOG.md
Project-URL: Documentation, https://opencv-pg.readthedocs.io/en/latest/
Project-URL: Homepage, https://github.com/opencv-pg/opencv-pg
Project-URL: Repository, https://github.com/opencv-pg/opencv-pg
Provides-Extra: dev
